{
	"isFor": 30,
	"desc": "CAR_PATROLLINGs",
	"tag": "CAR_PATROLLINGs",
	"locations": [{
		"x": -1926.6650390625,
		"district": "Watson",
		"inVehicule": true,
		"subdistrict": "LittleChina",
		"Tag": "CAR_PATROLLINGLCH_4",
		"y": 1050.62890625,
		"z": 11.92650604248
	}, {
		"Tag": "CAR_PATROLLINGs",
		"district": "Watson",
		"inVehicule": true,
		"subdistrict": "ArasakaWaterfront",
		"x": -817.56408691406,
		"y": 1424.7864990234,
		"z": 22.376533508301
	}, {
		"Tag": "CAR_PATROLLINGs",
		"district": "Watson",
		"inVehicule": true,
		"subdistrict": "ArasakaWaterfront",
		"x": -849.97717285156,
		"y": 1363.1213378906,
		"z": 22.27180480957
	}, {
		"Tag": "CAR_PATROLLINGs",
		"district": "Watson",
		"inVehicule": true,
		"subdistrict": "ArasakaWaterfront",
		"x": -882.77642822266,
		"y": 1292.7338867188,
		"z": 22.227409362793
	}, {
		"Tag": "CAR_PATROLLINGs",
		"district": "Watson",
		"inVehicule": true,
		"subdistrict": "ArasakaWaterfront",
		"x": -897.65057373047,
		"y": 1135.1225585938,
		"z": 20.948631286621
	}, {
		"Tag": "CAR_PATROLLINGs",
		"district": "Watson",
		"inVehicule": true,
		"subdistrict": "ArasakaWaterfront",
		"x": -894.74829101563,
		"y": 1086.3765869141,
		"z": 20.920295715332
	}, {
		"Tag": "CAR_PATROLLINGs",
		"district": "Watson",
		"inVehicule": true,
		"subdistrict": "ArasakaWaterfront",
		"x": -877.30627441406,
		"y": 983.27722167969,
		"z": 22.234840393066
	}, {
		"Tag": "CAR_PATROLLINGs",
		"district": "Watson",
		"inVehicule": true,
		"subdistrict": "ArasakaWaterfront",
		"x": -870.20245361328,
		"y": 919.72741699219,
		"z": 22.259605407715
	}, {
		"Tag": "CAR_PATROLLINGs",
		"district": "Watson",
		"inVehicule": true,
		"subdistrict": "ArasakaWaterfront",
		"x": -797.85961914063,
		"y": 941.65637207031,
		"z": 11.826927185059
	}, {
		"Tag": "CAR_PATROLLINGs",
		"district": "Watson",
		"inVehicule": true,
		"subdistrict": "ArasakaWaterfront",
		"x": -782.00183105469,
		"y": 1010.1380004883,
		"z": 11.826858520508
	}, {
		"Tag": "CAR_PATROLLINGs",
		"district": "Watson",
		"inVehicule": true,
		"subdistrict": "ArasakaWaterfront",
		"x": -713.86340332031,
		"y": 947.30480957031,
		"z": 11.826858520508
	}, {
		"Tag": "CAR_PATROLLINGs",
		"district": "Watson",
		"inVehicule": true,
		"subdistrict": "ArasakaWaterfront",
		"x": -506.94519042969,
		"y": 1057.4091796875,
		"z": 46.912956237793
	}, {
		"Tag": "CAR_PATROLLINGs",
		"district": "Watson",
		"inVehicule": true,
		"subdistrict": "ArasakaWaterfront",
		"x": -448.45849609375,
		"y": 1007.270324707,
		"z": 56.642539978027
	}, {
		"Tag": "CAR_PATROLLINGs",
		"district": "Watson",
		"inVehicule": true,
		"subdistrict": "ArasakaWaterfront",
		"x": -428.81167602539,
		"y": 993.87615966797,
		"z": 56.642433166504
	}, {
		"Tag": "CAR_PATROLLINGs",
		"district": "Watson",
		"inVehicule": true,
		"subdistrict": "ArasakaWaterfront",
		"x": -362.82653808594,
		"y": 948.88970947266,
		"z": 65.305160522461
	}, {
		"Tag": "CAR_PATROLLINGs",
		"district": "Watson",
		"inVehicule": true,
		"subdistrict": "ArasakaWaterfront",
		"x": -333.59674072266,
		"y": 955.34326171875,
		"z": 65.304824829102
	}, {
		"Tag": "CAR_PATROLLINGs",
		"district": "Watson",
		"inVehicule": true,
		"subdistrict": "ArasakaWaterfront",
		"x": -292.27114868164,
		"y": 1006.5178833008,
		"z": 65.295272827148
	}, {
		"Tag": "CAR_PATROLLINGs",
		"district": "Watson",
		"inVehicule": true,
		"subdistrict": "ArasakaWaterfront",
		"x": -255.41163635254,
		"y": 860.78576660156,
		"z": 77.125335693359
	}, {
		"Tag": "CAR_PATROLLINGs",
		"district": "Watson",
		"inVehicule": true,
		"subdistrict": "ArasakaWaterfront",
		"x": -378.98095703125,
		"y": 860.07946777344,
		"z": 64.842590332031
	}, {
		"Tag": "CAR_PATROLLINGs",
		"district": "Watson",
		"inVehicule": true,
		"subdistrict": "ArasakaWaterfront",
		"x": -411.3014831543,
		"y": 856.17175292969,
		"z": 64.76123046875
	}, {
		"Tag": "CAR_PATROLLINGs",
		"district": "Watson",
		"inVehicule": true,
		"subdistrict": "ArasakaWaterfront",
		"x": -705.11328125,
		"y": 434.97180175781,
		"z": 19.236824035645
	}, {
		"Tag": "CAR_PATROLLINGs",
		"district": "Watson",
		"inVehicule": true,
		"subdistrict": "ArasakaWaterfront",
		"x": -842.99572753906,
		"y": 35.372886657715,
		"z": 8
	}, {
		"Tag": "CAR_PATROLLINGs",
		"district": "Watson",
		"inVehicule": true,
		"subdistrict": "ArasakaWaterfront",
		"x": -876.83062744141,
		"y": -96.57487487793,
		"z": 7.0299987792969
	}, {
		"Tag": "CAR_PATROLLINGs",
		"district": "Watson",
		"inVehicule": true,
		"subdistrict": "ArasakaWaterfront",
		"x": -867.32189941406,
		"y": -118.17111206055,
		"z": 7.0375442504883
	}, {
		"Tag": "CAR_PATROLLINGs",
		"district": "Watson",
		"inVehicule": true,
		"subdistrict": "ArasakaWaterfront",
		"x": -845.17639160156,
		"y": -138.94860839844,
		"z": 7.1869125366211
	}, {
		"Tag": "CAR_PATROLLINGs",
		"district": "Watson",
		"inVehicule": true,
		"subdistrict": "ArasakaWaterfront",
		"x": -722.56713867188,
		"y": -222.11372375488,
		"z": 8.0033187866211
	}, {
		"Tag": "CAR_PATROLLINGs",
		"district": "Watson",
		"inVehicule": true,
		"subdistrict": "ArasakaWaterfront",
		"x": -725.78588867188,
		"y": -252.76069641113,
		"z": 8.0000305175781
	}, {
		"Tag": "CAR_PATROLLINGs",
		"district": "Watson",
		"inVehicule": true,
		"subdistrict": "ArasakaWaterfront",
		"x": -785.88934326172,
		"y": -336.64352416992,
		"z": 8
	}, {
		"Tag": "CAR_PATROLLINGs",
		"district": "Watson",
		"inVehicule": true,
		"subdistrict": "ArasakaWaterfront",
		"x": -738.93225097656,
		"y": -384.27084350586,
		"z": 8.0000762939453
	}, {
		"Tag": "CAR_PATROLLINGs",
		"district": "Watson",
		"inVehicule": true,
		"subdistrict": "ArasakaWaterfront",
		"x": -688.94885253906,
		"y": -439.55206298828,
		"z": 8.0000381469727
	}, {
		"Tag": "CAR_PATROLLINGs",
		"district": "Watson",
		"inVehicule": true,
		"subdistrict": "ArasakaWaterfront",
		"x": -745.19897460938,
		"y": -516.07342529297,
		"z": 8.0000305175781
	}, {
		"Tag": "CAR_PATROLLINGs",
		"district": "Watson",
		"inVehicule": true,
		"subdistrict": "ArasakaWaterfront",
		"x": -776.63818359375,
		"y": -554.47137451172,
		"z": 8
	}, {
		"Tag": "CAR_PATROLLINGs",
		"district": "Watson",
		"inVehicule": true,
		"subdistrict": "ArasakaWaterfront",
		"x": -815.69213867188,
		"y": -609.93103027344,
		"z": 8.0000228881836
	}, {
		"Tag": "CAR_PATROLLINGs",
		"district": "Watson",
		"inVehicule": true,
		"subdistrict": "ArasakaWaterfront",
		"x": -844.2060546875,
		"y": -680.76397705078,
		"z": 8.0000381469727
	}, {
		"Tag": "CAR_PATROLLINGs",
		"district": "Watson",
		"inVehicule": true,
		"subdistrict": "ArasakaWaterfront",
		"x": -1251.6658935547,
		"y": -1156.0179443359,
		"z": 12.184562683105
	}, {
		"Tag": "CAR_PATROLLINGs",
		"district": "Watson",
		"inVehicule": true,
		"subdistrict": "ArasakaWaterfront",
		"x": -1319.2696533203,
		"y": -1086.9281005859,
		"z": 12.041290283203
	}, {
		"Tag": "CAR_PATROLLINGs",
		"district": "Watson",
		"inVehicule": true,
		"subdistrict": "ArasakaWaterfront",
		"x": -1637.1395263672,
		"y": -1008.2531738281,
		"z": 8.9155120849609
	}, {
		"Tag": "CAR_PATROLLINGs",
		"district": "Watson",
		"inVehicule": true,
		"subdistrict": "ArasakaWaterfront",
		"x": -1700.5615234375,
		"y": -1014.3997192383,
		"z": 8.8000030517578
	}, {
		"Tag": "CAR_PATROLLINGs",
		"district": "Watson",
		"inVehicule": true,
		"subdistrict": "ArasakaWaterfront",
		"x": -1088.6037597656,
		"y": -639.70190429688,
		"z": 8.0080642700195
	}, {
		"Tag": "CAR_PATROLLINGs",
		"district": "Watson",
		"inVehicule": true,
		"subdistrict": "ArasakaWaterfront",
		"x": -1148.92578125,
		"y": -634.65826416016,
		"z": 8.0000534057617
	}, {
		"Tag": "CAR_PATROLLINGs",
		"district": "Watson",
		"inVehicule": true,
		"subdistrict": "ArasakaWaterfront",
		"x": -1236.6446533203,
		"y": -611.13781738281,
		"z": 8.0233993530273
	}, {
		"Tag": "CAR_PATROLLINGs",
		"district": "Watson",
		"inVehicule": true,
		"subdistrict": "ArasakaWaterfront",
		"x": -1330.8267822266,
		"y": -640.62158203125,
		"z": 7.5350646972656
	}, {
		"Tag": "CAR_PATROLLINGs",
		"district": "Watson",
		"inVehicule": true,
		"subdistrict": "ArasakaWaterfront",
		"x": -1341.2705078125,
		"y": -668.54644775391,
		"z": 7.5351181030273
	}, {
		"Tag": "CAR_PATROLLINGs",
		"district": "Watson",
		"inVehicule": true,
		"subdistrict": "ArasakaWaterfront",
		"x": -1421.1959228516,
		"y": -635.4423828125,
		"z": 7.5351104736328
	}, {
		"Tag": "CAR_PATROLLINGs",
		"district": "Watson",
		"inVehicule": true,
		"subdistrict": "ArasakaWaterfront",
		"x": -1434.8602294922,
		"y": -619.80828857422,
		"z": 7.5491561889648
	}, {
		"Tag": "CAR_PATROLLINGs",
		"district": "Watson",
		"inVehicule": true,
		"subdistrict": "ArasakaWaterfront",
		"x": -1475.5046386719,
		"y": -609.18420410156,
		"z": 7.4264755249023
	}, {
		"Tag": "CAR_PATROLLINGs",
		"district": "Watson",
		"inVehicule": true,
		"subdistrict": "ArasakaWaterfront",
		"x": -1493.0360107422,
		"y": -551.443359375,
		"z": 7.3762664794922
	}, {
		"Tag": "CAR_PATROLLINGs",
		"district": "Watson",
		"inVehicule": true,
		"subdistrict": "ArasakaWaterfront",
		"x": -1474.3713378906,
		"y": -535.23254394531,
		"z": 7.3655700683594
	}, {
		"Tag": "CAR_PATROLLINGs",
		"district": "Watson",
		"inVehicule": true,
		"subdistrict": "ArasakaWaterfront",
		"x": -1470.4471435547,
		"y": -486.95581054688,
		"z": 7.3469848632813
	}, {
		"Tag": "CAR_PATROLLINGs",
		"district": "Watson",
		"inVehicule": true,
		"subdistrict": "ArasakaWaterfront",
		"x": -1330.466796875,
		"y": -210.99063110352,
		"z": 7.9098205566406
	}, {
		"Tag": "CAR_PATROLLINGs",
		"district": "Watson",
		"inVehicule": true,
		"subdistrict": "ArasakaWaterfront",
		"x": -1250.681640625,
		"y": -187.20867919922,
		"z": 16.560325622559
	}, {
		"Tag": "CAR_PATROLLINGs",
		"district": "Watson",
		"inVehicule": true,
		"subdistrict": "ArasakaWaterfront",
		"x": -1400.1080322266,
		"y": -98.178283691406,
		"z": 16.652320861816
	}, {
		"Tag": "CAR_PATROLLINGs",
		"district": "Watson",
		"inVehicule": true,
		"subdistrict": "ArasakaWaterfront",
		"x": -1570.3543701172,
		"y": -20.011169433594,
		"z": 7.9316787719727
	}, {
		"Tag": "CAR_PATROLLINGs",
		"district": "Watson",
		"inVehicule": true,
		"subdistrict": "ArasakaWaterfront",
		"x": -1521.5417480469,
		"y": -197.29637145996,
		"z": 16.188758850098
	}, {
		"Tag": "CAR_PATROLLINGs",
		"district": "Watson",
		"inVehicule": true,
		"subdistrict": "ArasakaWaterfront",
		"x": -1509.8647460938,
		"y": -201.54248046875,
		"z": 16.139915466309
	}, {
		"Tag": "CAR_PATROLLINGs",
		"district": "Watson",
		"inVehicule": true,
		"subdistrict": "ArasakaWaterfront",
		"x": -1506.2469482422,
		"y": -219.49153137207,
		"z": 7.8957901000977
	}, {
		"Tag": "CAR_PATROLLINGs",
		"district": "Watson",
		"inVehicule": true,
		"subdistrict": "ArasakaWaterfront",
		"x": -1347.025390625,
		"y": -195.33422851563,
		"z": 7.906120300293
	}, {
		"Tag": "CAR_PATROLLINGs",
		"district": "Watson",
		"inVehicule": true,
		"subdistrict": "ArasakaWaterfront",
		"x": -1193.9519042969,
		"y": -47.268737792969,
		"z": 7.7147827148438
	}, {
		"Tag": "CAR_PATROLLINGs",
		"district": "Watson",
		"inVehicule": true,
		"subdistrict": "ArasakaWaterfront",
		"x": -1279.9799804688,
		"y": 116.70593261719,
		"z": 7.6691436767578
	}, {
		"Tag": "CAR_PATROLLINGs",
		"district": "Watson",
		"inVehicule": true,
		"subdistrict": "ArasakaWaterfront",
		"x": -1235.8895263672,
		"y": 177.52157592773,
		"z": 16.502410888672
	}, {
		"Tag": "CAR_PATROLLINGs",
		"district": "Watson",
		"inVehicule": true,
		"subdistrict": "ArasakaWaterfront",
		"x": -1235.3471679688,
		"y": 181.33506774902,
		"z": 7.5
	}, {
		"Tag": "CAR_PATROLLINGs",
		"district": "Watson",
		"inVehicule": true,
		"subdistrict": "ArasakaWaterfront",
		"x": -1322.2493896484,
		"y": 235.59419250488,
		"z": 6.6722183227539
	}, {
		"Tag": "CAR_PATROLLINGs",
		"district": "Watson",
		"inVehicule": true,
		"subdistrict": "ArasakaWaterfront",
		"x": -1576.5982666016,
		"y": 237.37693786621,
		"z": 7.7300033569336
	}, {
		"Tag": "CAR_PATROLLINGs",
		"district": "Watson",
		"inVehicule": true,
		"subdistrict": "ArasakaWaterfront",
		"x": -1573.9675292969,
		"y": 311.80773925781,
		"z": 7.980110168457
	}, {
		"Tag": "CAR_PATROLLINGs",
		"district": "Watson",
		"inVehicule": true,
		"subdistrict": "ArasakaWaterfront",
		"x": -1548.451171875,
		"y": 348.65103149414,
		"z": 7.9563827514648
	}, {
		"Tag": "CAR_PATROLLINGs",
		"district": "Watson",
		"inVehicule": true,
		"subdistrict": "ArasakaWaterfront",
		"x": -1514.6818847656,
		"y": 446.80978393555,
		"z": 7.540412902832
	}, {
		"Tag": "CAR_PATROLLINGs",
		"district": "Watson",
		"inVehicule": true,
		"subdistrict": "ArasakaWaterfront",
		"x": -1512.0869140625,
		"y": 517.611328125,
		"z": 8.0570602416992
	}, {
		"Tag": "CAR_PATROLLINGs",
		"district": "Watson",
		"inVehicule": true,
		"subdistrict": "ArasakaWaterfront",
		"x": -1511.5753173828,
		"y": 480.04858398438,
		"z": 7.7400665283203
	}, {
		"Tag": "CAR_PATROLLINGs",
		"district": "Watson",
		"inVehicule": true,
		"subdistrict": "ArasakaWaterfront",
		"x": -1514.0189208984,
		"y": 655.27044677734,
		"z": 8.7103805541992
	}, {
		"Tag": "CAR_PATROLLINGs",
		"district": "Watson",
		"inVehicule": true,
		"subdistrict": "ArasakaWaterfront",
		"x": -84.906188964844,
		"y": -157.43399047852,
		"z": 7.0054016113281
	}, {
		"Tag": "CAR_PATROLLINGs",
		"district": "Watson",
		"inVehicule": true,
		"subdistrict": "ArasakaWaterfront",
		"x": -117.67329406738,
		"y": -132.82536315918,
		"z": 6.9701080322266
	}, {
		"Tag": "CAR_PATROLLINGs",
		"district": "Watson",
		"inVehicule": true,
		"subdistrict": "ArasakaWaterfront",
		"x": -145.94088745117,
		"y": -112.6743927002,
		"z": 6.9701080322266
	}, {
		"Tag": "CAR_PATROLLINGs",
		"district": "Watson",
		"inVehicule": true,
		"subdistrict": "ArasakaWaterfront",
		"x": -181.07272338867,
		"y": -90.742553710938,
		"z": 7.0009841918945
	}, {
		"Tag": "CAR_PATROLLINGs",
		"district": "Watson",
		"inVehicule": true,
		"subdistrict": "ArasakaWaterfront",
		"x": -153.30143737793,
		"y": -30.847206115723,
		"z": 7.0001068115234
	}, {
		"Tag": "CAR_PATROLLINGs",
		"district": "Watson",
		"inVehicule": true,
		"subdistrict": "ArasakaWaterfront",
		"x": -152.13380432129,
		"y": -3.7100830078125,
		"z": 7.0000991821289
	}, {
		"Tag": "CAR_PATROLLINGs",
		"district": "Watson",
		"inVehicule": true,
		"subdistrict": "ArasakaWaterfront",
		"x": -223.41929626465,
		"y": 52.86994934082,
		"z": 12.000106811523
	}, {
		"Tag": "CAR_PATROLLINGs",
		"district": "Watson",
		"inVehicule": true,
		"subdistrict": "ArasakaWaterfront",
		"x": -197.03088378906,
		"y": 109.72280883789,
		"z": 12.931060791016
	}, {
		"Tag": "CAR_PATROLLINGs",
		"district": "Watson",
		"inVehicule": true,
		"subdistrict": "ArasakaWaterfront",
		"x": -146.92698669434,
		"y": 179.53765869141,
		"z": 14.437965393066
	}, {
		"Tag": "CAR_PATROLLINGs",
		"district": "Watson",
		"inVehicule": true,
		"subdistrict": "ArasakaWaterfront",
		"x": -203.32496643066,
		"y": 596.86206054688,
		"z": 74.232482910156
	}, {
		"Tag": "CAR_PATROLLINGs",
		"district": "Watson",
		"inVehicule": true,
		"subdistrict": "ArasakaWaterfront",
		"x": -182.51284790039,
		"y": 698.43920898438,
		"z": 77.530303955078
	}, {
		"Tag": "CAR_PATROLLINGs",
		"district": "Watson",
		"inVehicule": true,
		"subdistrict": "ArasakaWaterfront",
		"x": -114.90385437012,
		"y": 792.78753662109,
		"z": 81.356369018555
	}, {
		"Tag": "CAR_PATROLLINGs",
		"district": "Watson",
		"inVehicule": true,
		"subdistrict": "ArasakaWaterfront",
		"x": 80.162979125977,
		"y": 783.16857910156,
		"z": 128.875
	}, {
		"Tag": "CAR_PATROLLINGs",
		"district": "Watson",
		"inVehicule": true,
		"subdistrict": "ArasakaWaterfront",
		"x": 105.77616882324,
		"y": 776.11419677734,
		"z": 127.00608825684
	}, {
		"Tag": "CAR_PATROLLINGs",
		"district": "Watson",
		"inVehicule": true,
		"subdistrict": "ArasakaWaterfront",
		"x": -310.7453918457,
		"y": 1464.1550292969,
		"z": 41.948059082031
	}, {
		"Tag": "CAR_PATROLLINGs",
		"district": "Watson",
		"inVehicule": true,
		"subdistrict": "ArasakaWaterfront",
		"x": -992.39294433594,
		"y": 2504.4916992188,
		"z": 22.045806884766
	}, {
		"Tag": "CAR_PATROLLINGs",
		"district": "Watson",
		"inVehicule": true,
		"subdistrict": "ArasakaWaterfront",
		"x": -1050.056640625,
		"y": 2804.8125,
		"z": 22.13565826416
	}, {
		"Tag": "CAR_PATROLLINGs",
		"district": "Watson",
		"inVehicule": true,
		"subdistrict": "ArasakaWaterfront",
		"x": -1167.6369628906,
		"y": 2918.759765625,
		"z": 7.0377578735352
	}, {
		"Tag": "CAR_PATROLLINGs",
		"district": "Watson",
		"inVehicule": true,
		"subdistrict": "ArasakaWaterfront",
		"x": -1165.3690185547,
		"y": 2949.7238769531,
		"z": 6.986946105957
	}, {
		"Tag": "CAR_PATROLLINGs",
		"district": "Watson",
		"inVehicule": true,
		"subdistrict": "ArasakaWaterfront",
		"x": -1110.4353027344,
		"y": 3031.8840332031,
		"z": 6.9869766235352
	}, {
		"Tag": "CAR_PATROLLINGs",
		"district": "Watson",
		"inVehicule": true,
		"subdistrict": "ArasakaWaterfront",
		"x": -1082.0380859375,
		"y": 3074.1953125,
		"z": 6.9869918823242
	}, {
		"Tag": "CAR_PATROLLINGs",
		"district": "Watson",
		"inVehicule": true,
		"subdistrict": "ArasakaWaterfront",
		"x": -1049.9875488281,
		"y": 3077.984375,
		"z": 6.9866104125977
	}, {
		"Tag": "CAR_PATROLLINGs",
		"district": "Watson",
		"inVehicule": true,
		"subdistrict": "ArasakaWaterfront",
		"x": -1220.1862792969,
		"y": 2623.9152832031,
		"z": 6.9869155883789
	}, {
		"Tag": "CAR_PATROLLINGs",
		"district": "Watson",
		"inVehicule": true,
		"subdistrict": "ArasakaWaterfront",
		"x": -1409.8247070313,
		"y": 2708.8781738281,
		"z": 6.9869537353516
	}, {
		"Tag": "CAR_PATROLLINGs",
		"district": "Watson",
		"inVehicule": true,
		"subdistrict": "ArasakaWaterfront",
		"x": -1470.3311767578,
		"y": 2623.5776367188,
		"z": 6.986946105957
	}, {
		"Tag": "CAR_PATROLLINGs",
		"district": "Watson",
		"inVehicule": true,
		"subdistrict": "ArasakaWaterfront",
		"x": -1471.724609375,
		"y": 2580.494140625,
		"z": 6.9869918823242
	}, {
		"Tag": "CAR_PATROLLINGs",
		"district": "Watson",
		"inVehicule": true,
		"subdistrict": "ArasakaWaterfront",
		"x": -1386.3580322266,
		"y": 2341.7270507813,
		"z": 6.6473236083984
	}, {
		"Tag": "CAR_PATROLLINGs",
		"district": "Watson",
		"inVehicule": true,
		"subdistrict": "ArasakaWaterfront",
		"x": -1346.7103271484,
		"y": 2227.7351074219,
		"z": 15.769065856934
	}, {
		"Tag": "CAR_PATROLLINGs",
		"district": "Watson",
		"inVehicule": true,
		"subdistrict": "ArasakaWaterfront",
		"x": -1408.6716308594,
		"y": 2186.841796875,
		"z": 18.000061035156
	}, {
		"Tag": "CAR_PATROLLINGs",
		"district": "Watson",
		"inVehicule": true,
		"subdistrict": "ArasakaWaterfront",
		"x": -1345.5009765625,
		"y": 2069.5104980469,
		"z": 18
	}, {
		"Tag": "CAR_PATROLLINGs",
		"district": "Watson",
		"inVehicule": true,
		"subdistrict": "ArasakaWaterfront",
		"x": -1321.0196533203,
		"y": 2060.4777832031,
		"z": 18.000068664551
	}, {
		"Tag": "CAR_PATROLLINGs",
		"district": "Watson",
		"inVehicule": true,
		"subdistrict": "ArasakaWaterfront",
		"x": -1285.4841308594,
		"y": 2030.3703613281,
		"z": 18.051170349121
	}, {
		"Tag": "CAR_PATROLLINGs",
		"district": "Watson",
		"inVehicule": true,
		"subdistrict": "ArasakaWaterfront",
		"x": -1278.5701904297,
		"y": 1928.2033691406,
		"z": 18.01025390625
	}, {
		"Tag": "CAR_PATROLLINGs",
		"district": "Watson",
		"inVehicule": true,
		"subdistrict": "ArasakaWaterfront",
		"x": -1210.4674072266,
		"y": 1840.6632080078,
		"z": 22.303726196289
	}, {
		"Tag": "CAR_PATROLLINGs",
		"district": "Watson",
		"inVehicule": true,
		"subdistrict": "ArasakaWaterfront",
		"x": -1363.1434326172,
		"y": 1661.9206542969,
		"z": 18.000106811523
	}, {
		"Tag": "CAR_PATROLLINGs",
		"district": "Watson",
		"inVehicule": true,
		"subdistrict": "ArasakaWaterfront",
		"x": -1366.6221923828,
		"y": 1592.0963134766,
		"z": 18
	}, {
		"Tag": "CAR_PATROLLINGs",
		"district": "Watson",
		"inVehicule": true,
		"subdistrict": "ArasakaWaterfront",
		"x": -1370.7735595703,
		"y": 1539.9482421875,
		"z": 18.000045776367
	}, {
		"Tag": "CAR_PATROLLINGs",
		"district": "Watson",
		"inVehicule": true,
		"subdistrict": "ArasakaWaterfront",
		"x": -1397.0147705078,
		"y": 1442.2316894531,
		"z": 17.98999786377
	}, {
		"Tag": "CAR_PATROLLINGs",
		"district": "Watson",
		"inVehicule": true,
		"subdistrict": "ArasakaWaterfront",
		"x": -1402.263671875,
		"y": 1340.3361816406,
		"z": 14.495101928711
	}, {
		"Tag": "CAR_PATROLLINGs",
		"district": "Watson",
		"inVehicule": true,
		"subdistrict": "ArasakaWaterfront",
		"x": -1410.7431640625,
		"y": 1258.6643066406,
		"z": 14.5
	}, {
		"Tag": "CAR_PATROLLINGs",
		"district": "Watson",
		"inVehicule": true,
		"subdistrict": "ArasakaWaterfront",
		"x": -1423.1861572266,
		"y": 1199.0998535156,
		"z": 14.5
	}, {
		"Tag": "CAR_PATROLLINGs",
		"district": "Watson",
		"inVehicule": true,
		"subdistrict": "ArasakaWaterfront",
		"x": -1427.3074951172,
		"y": 1134.8629150391,
		"z": 22.851806640625
	}, {
		"Tag": "CAR_PATROLLINGs",
		"district": "Watson",
		"inVehicule": true,
		"subdistrict": "ArasakaWaterfront",
		"x": -1414.0751953125,
		"y": 1092.3940429688,
		"z": 22.86750793457
	}, {
		"Tag": "CAR_PATROLLINGs",
		"district": "Watson",
		"inVehicule": true,
		"subdistrict": "ArasakaWaterfront",
		"x": -1267.2309570313,
		"y": 1160.5362548828,
		"z": 16.722412109375
	}, {
		"Tag": "CAR_PATROLLINGs",
		"district": "Watson",
		"inVehicule": true,
		"subdistrict": "ArasakaWaterfront",
		"x": -1263.7791748047,
		"y": 1198.3447265625,
		"z": 16.790420532227
	}, {
		"Tag": "CAR_PATROLLINGs",
		"district": "Watson",
		"inVehicule": true,
		"subdistrict": "ArasakaWaterfront",
		"x": -1260.2758789063,
		"y": 1236.7160644531,
		"z": 16.820190429688
	}, {
		"Tag": "CAR_PATROLLINGs",
		"district": "Watson",
		"inVehicule": true,
		"subdistrict": "ArasakaWaterfront",
		"x": -1257.5474853516,
		"y": 1266.6013183594,
		"z": 16.820182800293
	}, {
		"Tag": "CAR_PATROLLINGs",
		"district": "Watson",
		"inVehicule": true,
		"subdistrict": "ArasakaWaterfront",
		"x": -1251.5837402344,
		"y": 1331.9232177734,
		"z": 20.779747009277
	}, {
		"Tag": "CAR_PATROLLINGs",
		"district": "Watson",
		"inVehicule": true,
		"subdistrict": "ArasakaWaterfront",
		"x": -1251.3940429688,
		"y": 1373.4230957031,
		"z": 20.780731201172
	}, {
		"Tag": "CAR_PATROLLINGs",
		"district": "Watson",
		"inVehicule": true,
		"subdistrict": "ArasakaWaterfront",
		"x": -1242.9873046875,
		"y": 1451.1164550781,
		"z": 20.779571533203
	}, {
		"Tag": "CAR_PATROLLINGs",
		"district": "Watson",
		"inVehicule": true,
		"subdistrict": "ArasakaWaterfront",
		"x": -1233.4985351563,
		"y": 1527.1190185547,
		"z": 22.612831115723
	}, {
		"Tag": "CAR_PATROLLINGs",
		"district": "Watson",
		"inVehicule": true,
		"subdistrict": "ArasakaWaterfront",
		"x": -1161.9381103516,
		"y": 1622.8465576172,
		"z": 22.243202209473
	}, {
		"Tag": "CAR_PATROLLINGs",
		"district": "Watson",
		"inVehicule": true,
		"subdistrict": "ArasakaWaterfront",
		"x": -1150.5471191406,
		"y": 1711.9118652344,
		"z": 22.773048400879
	}, {
		"Tag": "CAR_PATROLLINGs",
		"district": "Watson",
		"inVehicule": true,
		"subdistrict": "ArasakaWaterfront",
		"x": -1148.1710205078,
		"y": 1742.2282714844,
		"z": 22.799446105957
	}, {
		"Tag": "CAR_PATROLLINGs",
		"district": "Watson",
		"inVehicule": true,
		"subdistrict": "ArasakaWaterfront",
		"x": -1108.537109375,
		"y": 1790.4765625,
		"z": 24.558792114258
	}]
}